flask_rest_glue/__init__.py
flask_rest_glue/flask_endpoint.py
flask_rest_glue/misc.py
flask_rest_glue/openapi_spec.py
flask_restglue-0.0.4.dist-info/LICENSE
flask_restglue-0.0.4.dist-info/WHEEL
flask_restglue-0.0.4.dist-info/METADATA
flask_restglue-0.0.4.dist-info/RECORD
