Metadata-Version: 2.1
Name: flask-restglue
Version: 0.0.4
Summary: Flask-RestGlue integrates Flask, MongoDB, OpenAPI in a simple and elegant way
Home-page: https://github.com/abassel/Flask-RestGlue
License: MIT
Author: Alexandre Bassel
Author-email: abassel@abassel.com
Requires-Python: >=3.8,<4.0
Classifier: Development Status :: 3 - Alpha
Classifier: Framework :: Flask
Classifier: Intended Audience :: Developers
Classifier: License :: OSI Approved :: MIT License
Classifier: Operating System :: OS Independent
Classifier: Programming Language :: Python :: 3
Classifier: Programming Language :: Python :: 3.8
Classifier: Programming Language :: Python :: 3.9
Classifier: Topic :: Software Development :: Libraries :: Python Modules
Requires-Dist: Flask (>=1.1.2,<2.0.0)
Requires-Dist: importlib_metadata (>=1.6.0,<2.0.0); python_version < "3.8"
Requires-Dist: mongoengine (>=0.22.1,<0.23.0)
Requires-Dist: typer[all] (>=0.3.2,<0.4.0)
Project-URL: Repository, https://github.com/abassel/Flask-RestGlue
